goodfractions/__init__.py
goodfractions/_fraction.py
goodfractions-0.0.1.dist-info/licenses/LICENSE
tests/__init__.py
tests/test_empty.py
goodfractions-0.0.1.dist-info/METADATA
goodfractions-0.0.1.dist-info/WHEEL
goodfractions-0.0.1.dist-info/top_level.txt
goodfractions-0.0.1.dist-info/RECORD
